odoo8_addon_web_x2m_filter-8.0.1.0.0-py2.7-nspkg.pth
odoo_addons/web_x2m_filter/__openerp__.py
odoo_addons/web_x2m_filter/__init__.py
odoo_addons/web_x2m_filter/README.rst
odoo_addons/web_x2m_filter/views/templates.xml
odoo_addons/web_x2m_filter/demo/res_groups.xml
odoo_addons/web_x2m_filter/static/description/screenshot.png
odoo_addons/web_x2m_filter/static/description/icon.png
odoo_addons/web_x2m_filter/static/src/js/web_x2m_filter.js
odoo_addons/web_x2m_filter/static/src/css/web_x2m_filter.css
odoo_addons/web_x2m_filter/static/src/xml/web_x2m_filter.xml
odoo8_addon_web_x2m_filter-8.0.1.0.0.dist-info/top_level.txt
odoo8_addon_web_x2m_filter-8.0.1.0.0.dist-info/WHEEL
odoo8_addon_web_x2m_filter-8.0.1.0.0.dist-info/RECORD
odoo8_addon_web_x2m_filter-8.0.1.0.0.dist-info/metadata.json
odoo8_addon_web_x2m_filter-8.0.1.0.0.dist-info/DESCRIPTION.rst
odoo8_addon_web_x2m_filter-8.0.1.0.0.dist-info/METADATA
odoo8_addon_web_x2m_filter-8.0.1.0.0.dist-info/namespace_packages.txt
